MANIFEST.in
README.rst
setup.py
Products/__init__.py
Products.OpenXml.egg-info/PKG-INFO
Products.OpenXml.egg-info/SOURCES.txt
Products.OpenXml.egg-info/dependency_links.txt
Products.OpenXml.egg-info/namespace_packages.txt
Products.OpenXml.egg-info/not-zip-safe
Products.OpenXml.egg-info/requires.txt
Products.OpenXml.egg-info/top_level.txt
Products/OpenXml/HISTORY.txt
Products/OpenXml/LICENSE
Products/OpenXml/README.txt
Products/OpenXml/TODO
Products/OpenXml/__init__.py
Products/OpenXml/config.py
Products/OpenXml/configure.zcml
Products/OpenXml/setuphandlers.py
Products/OpenXml/transform.py
Products/OpenXml/utilities.py
Products/OpenXml/version.txt
Products/OpenXml/Extensions/__init__.py
Products/OpenXml/Extensions/install.py
Products/OpenXml/openxml-icons/docm.png
Products/OpenXml/openxml-icons/docx.png
Products/OpenXml/openxml-icons/dotm.png
Products/OpenXml/openxml-icons/dotx.png
Products/OpenXml/openxml-icons/potm.png
Products/OpenXml/openxml-icons/potx.png
Products/OpenXml/openxml-icons/ppam.png
Products/OpenXml/openxml-icons/ppsm.png
Products/OpenXml/openxml-icons/ppsx.png
Products/OpenXml/openxml-icons/pptm.png
Products/OpenXml/openxml-icons/pptx.png
Products/OpenXml/openxml-icons/xlam.png
Products/OpenXml/openxml-icons/xlsb.png
Products/OpenXml/openxml-icons/xlsm.png
Products/OpenXml/openxml-icons/xlsx.png
Products/OpenXml/openxml-icons/xltm.png
Products/OpenXml/openxml-icons/xltx.png
Products/OpenXml/profiles/default/import_steps.xml
Products/OpenXml/profiles/default/metadata.xml
Products/OpenXml/profiles/default/openxml_marker.txt
Products/OpenXml/tests/README.txt
Products/OpenXml/tests/__init__.py
Products/OpenXml/tests/common.py
Products/OpenXml/tests/test_mtr.py
Products/OpenXml/tests/test_pt.py
Products/OpenXml/tests/wordprocessing1.docx