Metadata-Version: 1.1
Name: Products.OpenXml
Version: 1.2.1
Summary: OpenXml documents support for Plone
Home-page: https://github.com/collective/Products.OpenXml
Author: Gilles Lenfant
Author-email: gilles.lenfant@gmail.com
License: GPLv2
Download-URL: http://plone.org/products/openxml
Keywords: Zope CMF Plone openxml
Platform: UNKNOWN
Classifier: Framework :: Plone
Classifier: Framework :: Zope2
Classifier: Programming Language :: Python
